Metadata-Version: 1.1
Name: django-C3PO
Version: 0.2.3
Summary: django-C3PO is a Django application using C3PO - module
